wallpapers/__init__.py
wallpapers/__main__.py
wallpapers/wallpapers.py
interfacelift_cli-0.2.2.dist-info/LICENSE.txt
interfacelift_cli-0.2.2.dist-info/METADATA
interfacelift_cli-0.2.2.dist-info/WHEEL
interfacelift_cli-0.2.2.dist-info/entry_points.txt
interfacelift_cli-0.2.2.dist-info/top_level.txt
interfacelift_cli-0.2.2.dist-info/RECORD
